main.py
gorgon/__init__.py
gorgon/crypto/__init__.py
gorgon/crypto/block/__init__.py
gorgon/crypto/block/block.py
gorgon/repository/__init__.py
gorgon/repository/proto.py
gorgon/utils/__init__.py
gorgon/utils/typing.py
gorgon_blockchain-0.0.1.dist-info/METADATA
gorgon_blockchain-0.0.1.dist-info/WHEEL
gorgon_blockchain-0.0.1.dist-info/RECORD
